borutashap_v2/__init__.py
borutashap_v2/boruta_shap.py
borutashap_v2-0.1.0.dist-info/licenses/LICENSE
borutashap_v2-0.1.0.dist-info/METADATA
borutashap_v2-0.1.0.dist-info/WHEEL
borutashap_v2-0.1.0.dist-info/top_level.txt
borutashap_v2-0.1.0.dist-info/RECORD
